{
  "project_info": {
    "project_number": "820733942677",
    "project_id": "sd-school-39034",
    "storage_bucket": "sd-school-39034.firebasestorage.app"
  },
  "client": [
    {
      "client_info": {
        "mobilesdk_app_id": "1:820733942677:android:78a0d5452bd0162aaa749c",
        "android_client_info": {
          "package_name": "com.sdschooleducation.apppro"
        }
      },
      "oauth_client": [],
      "api_key": [
        {
          "current_key": "AIzaSyBvh6U8xZW1DzwxbhKVudR8XNsF7YkGLG8"
        }
      ],
      "services": {
        "appinvite_service": {
          "other_platform_oauth_client": []
        }
      }
    }
  ],
  "configuration_version": "1"
}